Metadata-Version: 2.1
Name: ecmwf-data
Version: 0.0.1
Summary: A package to inspect and process meteorological data
Home-page: https://github.com/ecmwf/ecmwf-geomaps
Author: European Centre for Medium-Range Weather Forecasts (ECMWF)
Author-email: software.support@ecmwf.int
License: Apache License Version 2.0
Keywords: tool
Platform: UNKNOWN
Classifier: Development Status :: 3 - Alpha
Classifier: Intended Audience :: Developers
Classifier: License :: OSI Approved :: Apache Software License
Classifier: Programming Language :: Python :: 3
Classifier: Programming Language :: Python :: 3.6
Classifier: Programming Language :: Python :: 3.7
Classifier: Programming Language :: Python :: 3.8
Classifier: Programming Language :: Python :: Implementation :: CPython
Classifier: Programming Language :: Python :: Implementation :: PyPy
Classifier: Operating System :: OS Independent
License-File: LICENSE
